pynewhope/newhope.py
pynewhope/params.py
pynewhope/poly.py
pynewhope/precomp.py
PyNewHope-0.33.dist-info/LICENSE
PyNewHope-0.33.dist-info/METADATA
PyNewHope-0.33.dist-info/WHEEL
PyNewHope-0.33.dist-info/top_level.txt
PyNewHope-0.33.dist-info/RECORD
