Metadata-Version: 2.1
Name: PyNewHope
Version: 0.33
Summary: An experimental implementation of the NewHope post-quantum key exchange algorithm
Home-page: https://github.com/nakov/PyNewHope
Author: Scott Wyman Neagle, Svetlin Nakov
License: MIT
Download-URL: http://www.nakov.com
Keywords: NewHope,PQC,post-quantum-cryptography,key-exchange,cryptography
Platform: UNKNOWN
